odoo/addons/l10n_es_dua_ticketbai_batuz/README.rst
odoo/addons/l10n_es_dua_ticketbai_batuz/__init__.py
odoo/addons/l10n_es_dua_ticketbai_batuz/__manifest__.py
odoo/addons/l10n_es_dua_ticketbai_batuz/data/account_fiscal_position_template_data.xml
odoo/addons/l10n_es_dua_ticketbai_batuz/data/tax_code_map_dua_ticketbai_data.xml
odoo/addons/l10n_es_dua_ticketbai_batuz/i18n/es.po
odoo/addons/l10n_es_dua_ticketbai_batuz/i18n/eu.po
odoo/addons/l10n_es_dua_ticketbai_batuz/i18n/l10n_es_dua_ticketbai_batuz.pot
odoo/addons/l10n_es_dua_ticketbai_batuz/models/__init__.py
odoo/addons/l10n_es_dua_ticketbai_batuz/models/account_invoice.py
odoo/addons/l10n_es_dua_ticketbai_batuz/readme/CONFIGURATION.rst
odoo/addons/l10n_es_dua_ticketbai_batuz/readme/CONTRIBUTORS.rst
odoo/addons/l10n_es_dua_ticketbai_batuz/readme/DESCRIPTION.rst
odoo/addons/l10n_es_dua_ticketbai_batuz/readme/USAGE.rst
odoo/addons/l10n_es_dua_ticketbai_batuz/static/description/icon.png
odoo/addons/l10n_es_dua_ticketbai_batuz/static/description/index.html
odoo12_addon_l10n_es_dua_ticketbai_batuz-12.0.1.0.1.dist-info/METADATA
odoo12_addon_l10n_es_dua_ticketbai_batuz-12.0.1.0.1.dist-info/WHEEL
odoo12_addon_l10n_es_dua_ticketbai_batuz-12.0.1.0.1.dist-info/top_level.txt
odoo12_addon_l10n_es_dua_ticketbai_batuz-12.0.1.0.1.dist-info/RECORD
